rayvision_max/__init__.py
rayvision_max/analyse_max.py
rayvision_max/constants.py
rayvision_max/tests/__init__.py
rayvision_max/tests/conftest.py
rayvision_max/tests/test_analyse_max.py
rayvision_max/tool/7-zip.dll
rayvision_max/tool/7z.dll
rayvision_max/tool/7z.exe
rayvision_max/tool/MaxInfo.exe
rayvision_max/tool/analysea.mse
rayvision_max/tool/analysemax.exe
rayvision_max/tool/analyseu.mse
rayvision_max-1.2.8.dist-info/METADATA
rayvision_max-1.2.8.dist-info/WHEEL
rayvision_max-1.2.8.dist-info/top_level.txt
rayvision_max-1.2.8.dist-info/RECORD
